thp_package/DataMgmnt.py
thp_package/Jsondata.py
thp_package/MainTHP.py
thp_package/__init__.py
thp_package/datetimeTHP.py
thp_package-0.0.1.dist-info/LICENSE.txt
thp_package-0.0.1.dist-info/METADATA
thp_package-0.0.1.dist-info/WHEEL
thp_package-0.0.1.dist-info/top_level.txt
thp_package-0.0.1.dist-info/RECORD
