Metadata-Version: 2.1
Name: thp-package
Version: 0.0.1
Summary: Weather Monitoring
Home-page: UNKNOWN
Author: Prabhu Prasad Biswal
Author-email: prabhuprasadbiswal5@gmail.com
License: IISERm
Platform: UNKNOWN
Requires-Python: >=3.7
Requires-Dist: numpy
Requires-Dist: pandas
